lavender_github/__init__.py
lavender_github/artifact/__init__.py
lavender_github/artifact/delete_artifact.py
lavender_github/artifact/get_artifact_list.py
lavender_github/deployment/__init__.py
lavender_github/deployment/delete_deployment.py
lavender_github/deployment/get_deployment_list.py
lavender_github/repository/__init__.py
lavender_github/repository/get_repository_list.py
Lavender_GitHub-1.0.4.dist-info/LICENSE
Lavender_GitHub-1.0.4.dist-info/METADATA
Lavender_GitHub-1.0.4.dist-info/WHEEL
Lavender_GitHub-1.0.4.dist-info/top_level.txt
Lavender_GitHub-1.0.4.dist-info/RECORD
