Metadata-Version: 2.1
Name: Lavender-GitHub
Version: 1.0.4
Summary: A python package built with GitHub REST API.
Home-page: https://github.com/Zeyu-Xie/Lavender-GitHub
Author: Zeyu Xie
Author-email: xie.zeyu20@gmail.com
Classifier: Programming Language :: Python :: 3
Classifier: License :: OSI Approved :: GNU General Public License v3 (GPLv3)
Classifier: Operating System :: OS Independent
Requires-Python: >=3.6
License-File: LICENSE
